tkFontChooser.py
tkfontchooser.py
tkfontchooser-2.0.1.dist-info/DESCRIPTION.rst
tkfontchooser-2.0.1.dist-info/METADATA
tkfontchooser-2.0.1.dist-info/RECORD
tkfontchooser-2.0.1.dist-info/WHEEL
tkfontchooser-2.0.1.dist-info/metadata.json
tkfontchooser-2.0.1.dist-info/top_level.txt
